fastTF/__init__.py
fastTF/app.py
fastTF-1.0.3.dist-info/METADATA
fastTF-1.0.3.dist-info/WHEEL
fastTF-1.0.3.dist-info/top_level.txt
fastTF-1.0.3.dist-info/RECORD
