Metadata-Version: 2.1
Name: fastTF
Version: 1.0.3
Summary: Converts Pandas Dataframe to Tensorflow TFRecord
Home-page: https://github.com/azfar154/fastTF
Author: Azfar Mohamed
Author-email: azfarmah@outlook.com
License: UNKNOWN
Platform: UNKNOWN
Classifier: Programming Language :: Python :: 3
Classifier: License :: OSI Approved :: MIT License
Classifier: Operating System :: OS Independent
Requires-Python: >=3.6
Requires-Dist: pandas
Requires-Dist: tensorflow (>=2.0.0)
